strip_marks/__init__.py
strip_marks/strip_marks.py
strip_marks-1.0.1.dist-info/licenses/LICENSE
strip_marks-1.0.1.dist-info/METADATA
strip_marks-1.0.1.dist-info/WHEEL
strip_marks-1.0.1.dist-info/top_level.txt
strip_marks-1.0.1.dist-info/RECORD
