Metadata-Version: 2.4
Name: strip-marks
Version: 1.0.1
Summary: Small Python library to strip non-spacing marks (e.g., diacritics) from a string
Author-email: "Jake W. Ireland" <jakewilliami@icloud.com>
License: MIT
Project-URL: Repository, https://github.com/jakewilliami/strip-marks-py
Project-URL: PyPI, https://pypi.org/p/strip-marks
Requires-Python: <4.0.0,>=3.11
License-File: LICENSE
Requires-Dist: ispunct>=1.0.4
Dynamic: license-file
